workforcerappi/__init__.py
workforcerappi/costs.py
workforcerappi/data_processing.py
workforcerappi/dbconn.py
workforcerappi/fetch_data.py
workforcerappi/main.py
workforcerappi/modeling.py
workforcerappi/order_distribution.py
workforcerappi/reporting.py
workforcerappi-0.3.0.dist-info/METADATA
workforcerappi-0.3.0.dist-info/WHEEL
workforcerappi-0.3.0.dist-info/top_level.txt
workforcerappi-0.3.0.dist-info/RECORD
