Metadata-Version: 2.1
Name: workforcerappi
Version: 0.3.0
Requires-Dist: pandas ==2.1.4
Requires-Dist: numpy ==1.26.4
Requires-Dist: scikit-learn ==1.3.2
Requires-Dist: xgboost ==2.0.3
Requires-Dist: snowflake-connector-python ==3.7.1
Requires-Dist: snowflake-snowpark-python ==1.13.0
Requires-Dist: pyarrow ==16.1.0
Requires-Dist: seaborn ==0.13.2
Requires-Dist: matplotlib ==3.9.0
Requires-Dist: ipykernel ==6.29.4
Requires-Dist: openpyxl ==3.1.5
